kard/__init__.py
kard/auth/__init__.py
kard/auth/client.py
kard/auth/raw_client.py
kard/auth/types/__init__.py
kard/auth/types/token_response.py
kard/client.py
kard/commons/__init__.py
kard/commons/errors/__init__.py
kard/commons/errors/conflict_error.py
kard/commons/errors/does_not_exist_error.py
kard/commons/errors/internal_server_error.py
kard/commons/errors/invalid_request.py
kard/commons/errors/unauthorized_error.py
kard/commons/types/__init__.py
kard/commons/types/category_option.py
kard/commons/types/commission_type.py
kard/commons/types/commission_value.py
kard/commons/types/commission_value_type.py
kard/commons/types/empty_object.py
kard/commons/types/enrolled_rewards_type.py
kard/commons/types/error_object.py
kard/commons/types/error_response.py
kard/commons/types/error_source.py
kard/commons/types/job.py
kard/commons/types/job_response.py
kard/commons/types/job_status.py
kard/commons/types/links.py
kard/commons/types/mongo_id.py
kard/commons/types/notification_type.py
kard/commons/types/organization_id.py
kard/commons/types/purchase_channel.py
kard/commons/types/relationship_data.py
kard/commons/types/relationship_multiple.py
kard/commons/types/relationship_single.py
kard/commons/types/resource_type.py
kard/commons/types/state.py
kard/commons/types/subscription_id.py
kard/commons/types/user_id.py
kard/core/__init__.py
kard/core/api_error.py
kard/core/client_wrapper.py
kard/core/datetime_utils.py
kard/core/file.py
kard/core/force_multipart.py
kard/core/http_client.py
kard/core/http_response.py
kard/core/http_sse/__init__.py
kard/core/http_sse/_api.py
kard/core/http_sse/_decoders.py
kard/core/http_sse/_exceptions.py
kard/core/http_sse/_models.py
kard/core/jsonable_encoder.py
kard/core/oauth_token_provider.py
kard/core/pydantic_utilities.py
kard/core/query_encoder.py
kard/core/remove_none_from_dict.py
kard/core/request_options.py
kard/core/serialization.py
kard/environment.py
kard/files/__init__.py
kard/files/client.py
kard/files/errors/__init__.py
kard_financial_sdk-2.0.0.dist-info/METADATA
kard_financial_sdk-2.0.0.dist-info/WHEEL
kard_financial_sdk-2.0.0.dist-info/RECORD
